{
    "openapi": "3.0.0",
    "info": {
        "title": "UCM — User Centralized Management API",
        "description": "API สำหรับระบบภายนอกที่ต้องการใช้ UCM เป็น Authentication & Permission Hub\n\n## วิธีการ Authenticate\n\n### 1. OAuth 2.0 / OIDC (แนะนำ — SSO)\n- **Authorization Code + PKCE**: สำหรับ web app / SPA ที่มีผู้ใช้ login\n- **Client Credentials**: สำหรับ M2M / server-to-server\n- รับ `access_token` (RS256 JWT) มาใช้เป็น `Bearer` header\n\n### 2. Sanctum Token (legacy)\n- POST /api/auth/user-login → รับ Sanctum token\n- POST /api/auth/token → admin token (server-to-server)\n\n## OIDC Discovery\nดู endpoint metadata ทั้งหมดได้ที่ `GET /.well-known/openid-configuration`",
        "contact": {
            "name": "UCM Admin"
        },
        "version": "2.0.0"
    },
    "servers": [
        {
            "url": "/user-centralized-managment/api",
            "description": "UCM API Server"
        }
    ],
    "paths": {
        "/auth/user-login": {
            "post": {
                "tags": [
                    "Authentication"
                ],
                "summary": "User Login",
                "description": "Authenticate ผู้ใช้ทั่วไปด้วย LDAP credentials แล้วรับ Sanctum token + permissions\n\n**Token Expiry:** 24 ชั่วโมง (ปรับได้ด้วย `UCM_USER_TOKEN_TTL_HOURS` ใน `.env`)\n\n**Rate Limit:** 10 requests / minute per IP",
                "operationId": "userLogin",
                "requestBody": {
                    "required": true,
                    "content": {
                        "application/json": {
                            "schema": {
                                "required": [
                                    "username",
                                    "password"
                                ],
                                "properties": {
                                    "username": {
                                        "description": "AD username",
                                        "type": "string",
                                        "example": "john.doe",
                                        "maxLength": 100
                                    },
                                    "password": {
                                        "type": "string",
                                        "format": "password",
                                        "example": "secret",
                                        "maxLength": 200
                                    },
                                    "system": {
                                        "description": "Slug ของระบบ (optional)",
                                        "type": "string",
                                        "example": "repair-system",
                                        "nullable": true,
                                        "maxLength": 100
                                    }
                                },
                                "type": "object"
                            }
                        }
                    }
                },
                "responses": {
                    "200": {
                        "description": "Login สำเร็จ",
                        "content": {
                            "application/json": {
                                "schema": {
                                    "properties": {
                                        "token": {
                                            "type": "string",
                                            "example": "1|AbCdEfGhIjKl..."
                                        },
                                        "type": {
                                            "type": "string",
                                            "example": "Bearer"
                                        },
                                        "expires_at": {
                                            "description": "เวลาหมดอายุของ token (ISO 8601)",
                                            "type": "string",
                                            "format": "date-time",
                                            "example": "2026-03-25T10:00:00+07:00"
                                        },
                                        "user": {
                                            "$ref": "#/components/schemas/UserProfile"
                                        },
                                        "permissions": {
                                            "type": "array",
                                            "items": {
                                                "type": "string"
                                            },
                                            "example": [
                                                "view_report",
                                                "edit_order"
                                            ]
                                        }
                                    },
                                    "type": "object"
                                }
                            }
                        }
                    },
                    "401": {
                        "description": "Credentials ผิด",
                        "content": {
                            "application/json": {
                                "schema": {
                                    "$ref": "#/components/schemas/ErrorResponse"
                                }
                            }
                        }
                    },
                    "403": {
                        "description": "ไม่มีบัญชีใน UCM หรือ account ถูก deactivate",
                        "content": {
                            "application/json": {
                                "schema": {
                                    "$ref": "#/components/schemas/ErrorResponse"
                                }
                            }
                        }
                    },
                    "422": {
                        "description": "Validation ผิดพลาด",
                        "content": {
                            "application/json": {
                                "schema": {
                                    "$ref": "#/components/schemas/ValidationError"
                                }
                            }
                        }
                    },
                    "429": {
                        "description": "Rate limit เกิน",
                        "content": {
                            "application/json": {
                                "schema": {
                                    "$ref": "#/components/schemas/ErrorResponse"
                                }
                            }
                        }
                    }
                }
            }
        },
        "/auth/token": {
            "post": {
                "tags": [
                    "Authentication"
                ],
                "summary": "Admin Token (server-to-server)",
                "description": "ออก long-lived token ด้วย admin LDAP credentials สำหรับระบบ legacy\n\nToken ไม่หมดอายุ — ยกเลิกด้วย DELETE /auth/token",
                "operationId": "issueAdminToken",
                "requestBody": {
                    "required": true,
                    "content": {
                        "application/json": {
                            "schema": {
                                "required": [
                                    "username",
                                    "password",
                                    "token_name"
                                ],
                                "properties": {
                                    "username": {
                                        "type": "string",
                                        "example": "admin"
                                    },
                                    "password": {
                                        "type": "string",
                                        "format": "password",
                                        "example": "secret"
                                    },
                                    "token_name": {
                                        "description": "ชื่อ token (unique — ออกซ้ำแทนที่ของเดิม)",
                                        "type": "string",
                                        "example": "repair-system",
                                        "maxLength": 100
                                    }
                                },
                                "type": "object"
                            }
                        }
                    }
                },
                "responses": {
                    "200": {
                        "description": "Token ออกสำเร็จ",
                        "content": {
                            "application/json": {
                                "schema": {
                                    "properties": {
                                        "token": {
                                            "type": "string",
                                            "example": "2|XyZaBcDeFgHi..."
                                        },
                                        "type": {
                                            "type": "string",
                                            "example": "Bearer"
                                        }
                                    },
                                    "type": "object"
                                }
                            }
                        }
                    },
                    "401": {
                        "description": "Credentials ผิด",
                        "content": {
                            "application/json": {
                                "schema": {
                                    "$ref": "#/components/schemas/ErrorResponse"
                                }
                            }
                        }
                    },
                    "403": {
                        "description": "Account ไม่ใช่ admin",
                        "content": {
                            "application/json": {
                                "schema": {
                                    "$ref": "#/components/schemas/ErrorResponse"
                                }
                            }
                        }
                    }
                }
            },
            "delete": {
                "tags": [
                    "Authentication"
                ],
                "summary": "Logout / Revoke Token",
                "description": "ลบ token ที่ใช้ส่งมาทิ้ง ใช้ได้ทั้ง admin token และ user token",
                "operationId": "revokeToken",
                "responses": {
                    "200": {
                        "description": "Token ถูกยกเลิกแล้ว",
                        "content": {
                            "application/json": {
                                "schema": {
                                    "properties": {
                                        "message": {
                                            "type": "string",
                                            "example": "Token revoked"
                                        }
                                    },
                                    "type": "object"
                                }
                            }
                        }
                    },
                    "400": {
                        "description": "ไม่พบ active token ใน request นี้",
                        "content": {
                            "application/json": {
                                "schema": {
                                    "$ref": "#/components/schemas/ErrorResponse"
                                }
                            }
                        }
                    },
                    "401": {
                        "description": "ไม่มี token",
                        "content": {
                            "application/json": {
                                "schema": {
                                    "$ref": "#/components/schemas/ErrorResponse"
                                }
                            }
                        }
                    }
                },
                "security": [
                    {
                        "bearerAuth": []
                    }
                ]
            }
        },
        "/permissions/check": {
            "post": {
                "tags": [
                    "Permissions"
                ],
                "summary": "ตรวจสอบ Permission (real-time)",
                "description": "เช็คว่า user มี permission key ใดๆ ในระบบที่ระบุ เหมาะสำหรับใช้ใน middleware\n\n**Token Scope:**\n- Admin token (จาก `/auth/token`) — query ได้ทุก user\n- User token (จาก `/auth/user-login`) — query ได้เฉพาะ username ของตัวเอง",
                "operationId": "checkPermission",
                "requestBody": {
                    "required": true,
                    "content": {
                        "application/json": {
                            "schema": {
                                "required": [
                                    "username",
                                    "system",
                                    "permission"
                                ],
                                "properties": {
                                    "username": {
                                        "type": "string",
                                        "example": "john.doe",
                                        "maxLength": 100
                                    },
                                    "system": {
                                        "description": "Slug ของระบบ",
                                        "type": "string",
                                        "example": "repair-system",
                                        "maxLength": 100
                                    },
                                    "permission": {
                                        "description": "Permission key",
                                        "type": "string",
                                        "example": "approve",
                                        "maxLength": 100
                                    }
                                },
                                "type": "object"
                            }
                        }
                    }
                },
                "responses": {
                    "200": {
                        "description": "ผลการตรวจสอบ (200 เสมอ — ดู allowed field)",
                        "content": {
                            "application/json": {
                                "schema": {
                                    "properties": {
                                        "allowed": {
                                            "type": "boolean",
                                            "example": true
                                        },
                                        "reason": {
                                            "type": "string",
                                            "example": "user_not_found",
                                            "nullable": true
                                        }
                                    },
                                    "type": "object"
                                }
                            }
                        }
                    },
                    "401": {
                        "description": "ไม่มี token",
                        "content": {
                            "application/json": {
                                "schema": {
                                    "$ref": "#/components/schemas/ErrorResponse"
                                }
                            }
                        }
                    },
                    "403": {
                        "description": "User token พยายาม query ข้อมูลของผู้ใช้คนอื่น",
                        "content": {
                            "application/json": {
                                "schema": {
                                    "$ref": "#/components/schemas/ErrorResponse"
                                }
                            }
                        }
                    }
                },
                "security": [
                    {
                        "bearerAuth": []
                    }
                ]
            }
        },
        "/users/{username}/permissions": {
            "get": {
                "tags": [
                    "Permissions"
                ],
                "summary": "ดึง permissions ของ user ในระบบที่ระบุ",
                "description": "คืน array ของ permission keys ทั้งหมดที่ user มีในระบบนั้น\n\n**Token Scope:**\n- Admin token (จาก `/auth/token`) — query ได้ทุก user\n- User token (จาก `/auth/user-login`) — query ได้เฉพาะ username ของตัวเอง",
                "operationId": "getUserPermissions",
                "parameters": [
                    {
                        "name": "username",
                        "in": "path",
                        "description": "UCM username",
                        "required": true,
                        "schema": {
                            "type": "string",
                            "example": "john.doe"
                        }
                    },
                    {
                        "name": "system",
                        "in": "query",
                        "description": "Slug ของระบบ",
                        "required": true,
                        "schema": {
                            "type": "string",
                            "example": "repair-system"
                        }
                    }
                ],
                "responses": {
                    "200": {
                        "description": "Permissions ของ user",
                        "content": {
                            "application/json": {
                                "schema": {
                                    "properties": {
                                        "username": {
                                            "type": "string",
                                            "example": "john.doe"
                                        },
                                        "system": {
                                            "type": "string",
                                            "example": "repair-system"
                                        },
                                        "permissions": {
                                            "type": "array",
                                            "items": {
                                                "type": "string"
                                            },
                                            "example": [
                                                "view_report",
                                                "edit_order"
                                            ]
                                        }
                                    },
                                    "type": "object"
                                }
                            }
                        }
                    },
                    "401": {
                        "description": "ไม่มี token",
                        "content": {
                            "application/json": {
                                "schema": {
                                    "$ref": "#/components/schemas/ErrorResponse"
                                }
                            }
                        }
                    },
                    "403": {
                        "description": "User token พยายาม query ข้อมูลของผู้ใช้คนอื่น",
                        "content": {
                            "application/json": {
                                "schema": {
                                    "$ref": "#/components/schemas/ErrorResponse"
                                }
                            }
                        }
                    },
                    "404": {
                        "description": "ไม่พบ user หรือ system",
                        "content": {
                            "application/json": {
                                "schema": {
                                    "$ref": "#/components/schemas/ErrorResponse"
                                }
                            }
                        }
                    }
                },
                "security": [
                    {
                        "bearerAuth": []
                    }
                ]
            }
        },
        "/users/{username}/permissions/all": {
            "get": {
                "tags": [
                    "Permissions"
                ],
                "summary": "ดึง permissions ของ user ในทุกระบบ",
                "description": "คืน permissions แบบ group by system slug ในคำสั่งเดียว (single JOIN query — ไม่มี N+1)\n\n**Token Scope:**\n- Admin token (จาก `/auth/token`) — query ได้ทุก user\n- User token (จาก `/auth/user-login`) — query ได้เฉพาะ username ของตัวเอง",
                "operationId": "getAllSystemsPermissions",
                "parameters": [
                    {
                        "name": "username",
                        "in": "path",
                        "description": "UCM username",
                        "required": true,
                        "schema": {
                            "type": "string",
                            "example": "john.doe"
                        }
                    }
                ],
                "responses": {
                    "200": {
                        "description": "Permissions ของ user ในทุกระบบที่ active",
                        "content": {
                            "application/json": {
                                "schema": {
                                    "properties": {
                                        "username": {
                                            "type": "string",
                                            "example": "john.doe"
                                        },
                                        "systems": {
                                            "type": "object",
                                            "example": {
                                                "repair-system": [
                                                    "view_report",
                                                    "edit_order"
                                                ],
                                                "hr-system": [
                                                    "view_employee"
                                                ]
                                            },
                                            "additionalProperties": {
                                                "type": "array",
                                                "items": {
                                                    "type": "string"
                                                }
                                            }
                                        }
                                    },
                                    "type": "object"
                                }
                            }
                        }
                    },
                    "401": {
                        "description": "ไม่มี token",
                        "content": {
                            "application/json": {
                                "schema": {
                                    "$ref": "#/components/schemas/ErrorResponse"
                                }
                            }
                        }
                    },
                    "403": {
                        "description": "User token พยายาม query ข้อมูลของผู้ใช้คนอื่น",
                        "content": {
                            "application/json": {
                                "schema": {
                                    "$ref": "#/components/schemas/ErrorResponse"
                                }
                            }
                        }
                    },
                    "404": {
                        "description": "ไม่พบ user",
                        "content": {
                            "application/json": {
                                "schema": {
                                    "$ref": "#/components/schemas/ErrorResponse"
                                }
                            }
                        }
                    }
                },
                "security": [
                    {
                        "bearerAuth": []
                    }
                ]
            }
        },
        "/users/export": {
            "get": {
                "tags": [
                    "Export"
                ],
                "summary": "ส่งออกข้อมูลผู้ใช้ + permissions ทุกระบบ",
                "description": "ดึงข้อมูลผู้ใช้ (username, employee_number, name, email, department, title) พร้อม permissions ทุกระบบที่ active\n\n- ถ้าไม่ส่ง filter จะดึงผู้ใช้ทั้งหมด\n- กรองด้วย `user_ids[]` หรือ `usernames[]` ได้ (เลือกอย่างใดอย่างหนึ่ง)\n- permissions จัด group ตาม system slug",
                "operationId": "exportUsers",
                "parameters": [
                    {
                        "name": "user_ids[]",
                        "in": "query",
                        "description": "กรอง user ด้วย UCM user ID (ส่งได้หลายค่า)",
                        "required": false,
                        "schema": {
                            "type": "array",
                            "items": {
                                "type": "integer"
                            }
                        },
                        "example": [
                            1,
                            2,
                            3
                        ]
                    },
                    {
                        "name": "usernames[]",
                        "in": "query",
                        "description": "กรอง user ด้วย username (ใช้แทน user_ids ได้)",
                        "required": false,
                        "schema": {
                            "type": "array",
                            "items": {
                                "type": "string"
                            }
                        },
                        "example": [
                            "john.doe",
                            "jane.smith"
                        ]
                    }
                ],
                "responses": {
                    "200": {
                        "description": "ข้อมูลผู้ใช้ + permissions",
                        "content": {
                            "application/json": {
                                "schema": {
                                    "properties": {
                                        "count": {
                                            "type": "integer",
                                            "example": 2
                                        },
                                        "exported": {
                                            "type": "string",
                                            "format": "date-time",
                                            "example": "2026-03-21T10:00:00+07:00"
                                        },
                                        "users": {
                                            "type": "array",
                                            "items": {
                                                "properties": {
                                                    "username": {
                                                        "type": "string",
                                                        "example": "john.doe"
                                                    },
                                                    "employee_number": {
                                                        "type": "string",
                                                        "example": "EMP001",
                                                        "nullable": true
                                                    },
                                                    "name": {
                                                        "type": "string",
                                                        "example": "John Doe"
                                                    },
                                                    "email": {
                                                        "type": "string",
                                                        "example": "john@company.com",
                                                        "nullable": true
                                                    },
                                                    "department": {
                                                        "type": "string",
                                                        "example": "IT",
                                                        "nullable": true
                                                    },
                                                    "title": {
                                                        "type": "string",
                                                        "example": "Developer",
                                                        "nullable": true
                                                    },
                                                    "systems": {
                                                        "description": "permissions จัด group ตาม system slug",
                                                        "type": "object",
                                                        "example": {
                                                            "repair-system": [
                                                                "view_report",
                                                                "edit_order"
                                                            ],
                                                            "hr-system": [
                                                                "view_employee"
                                                            ]
                                                        },
                                                        "additionalProperties": {
                                                            "type": "array",
                                                            "items": {
                                                                "type": "string"
                                                            }
                                                        }
                                                    }
                                                },
                                                "type": "object"
                                            }
                                        }
                                    },
                                    "type": "object"
                                }
                            }
                        }
                    },
                    "401": {
                        "description": "ไม่มี token",
                        "content": {
                            "application/json": {
                                "schema": {
                                    "$ref": "#/components/schemas/ErrorResponse"
                                }
                            }
                        }
                    }
                },
                "security": [
                    {
                        "bearerAuth": []
                    }
                ]
            }
        },
        "/oauth/token": {
            "post": {
                "tags": [
                    "OAuth 2.0"
                ],
                "summary": "Token Endpoint (OAuth 2.0)",
                "description": "ออก access_token / refresh_token ด้วย 3 grant types:\n\n**authorization_code** — แลก authorization code เป็น tokens (ต้องส่ง code_verifier ถ้าใช้ PKCE)\n\n**refresh_token** — ต่ออายุ token (rotation: refresh token เก่าถูก revoke)\n\n**client_credentials** — M2M token (ต้องใช้ confidential client)\n\n**Rate Limit:** 60 requests / minute",
                "operationId": "oauthToken",
                "requestBody": {
                    "required": true,
                    "content": {
                        "application/x-www-form-urlencoded": {
                            "schema": {
                                "required": [
                                    "grant_type"
                                ],
                                "properties": {
                                    "grant_type": {
                                        "type": "string",
                                        "example": "authorization_code",
                                        "enum": [
                                            "authorization_code",
                                            "refresh_token",
                                            "client_credentials"
                                        ]
                                    },
                                    "client_id": {
                                        "description": "ส่งใน body หรือ HTTP Basic auth",
                                        "type": "string",
                                        "example": "ucm_AbCdEf..."
                                    },
                                    "client_secret": {
                                        "description": "สำหรับ confidential client",
                                        "type": "string",
                                        "example": "secret..."
                                    },
                                    "code": {
                                        "description": "authorization_code grant",
                                        "type": "string"
                                    },
                                    "redirect_uri": {
                                        "description": "authorization_code grant",
                                        "type": "string",
                                        "format": "uri"
                                    },
                                    "code_verifier": {
                                        "description": "PKCE verifier (authorization_code + PKCE)",
                                        "type": "string"
                                    },
                                    "refresh_token": {
                                        "description": "refresh_token grant",
                                        "type": "string"
                                    },
                                    "scope": {
                                        "description": "client_credentials grant",
                                        "type": "string",
                                        "example": "openid profile"
                                    }
                                },
                                "type": "object"
                            }
                        }
                    }
                },
                "responses": {
                    "200": {
                        "description": "Token ออกสำเร็จ",
                        "content": {
                            "application/json": {
                                "schema": {
                                    "properties": {
                                        "access_token": {
                                            "type": "string",
                                            "example": "eyJhbGci..."
                                        },
                                        "token_type": {
                                            "type": "string",
                                            "example": "Bearer"
                                        },
                                        "expires_in": {
                                            "type": "integer",
                                            "example": 3600
                                        },
                                        "refresh_token": {
                                            "type": "string",
                                            "example": "XyZaBcDe...",
                                            "nullable": true
                                        },
                                        "id_token": {
                                            "description": "ส่งเมื่อ scope มี openid",
                                            "type": "string",
                                            "example": "eyJhbGci...",
                                            "nullable": true
                                        },
                                        "scope": {
                                            "type": "string",
                                            "example": "openid profile"
                                        }
                                    },
                                    "type": "object"
                                }
                            }
                        }
                    },
                    "400": {
                        "description": "invalid_grant / invalid_client / unsupported_grant_type",
                        "content": {
                            "application/json": {
                                "schema": {
                                    "properties": {
                                        "error": {
                                            "type": "string",
                                            "example": "invalid_grant"
                                        },
                                        "error_description": {
                                            "type": "string"
                                        }
                                    },
                                    "type": "object"
                                }
                            }
                        }
                    }
                }
            }
        },
        "/oauth/token/revoke": {
            "post": {
                "tags": [
                    "OAuth 2.0"
                ],
                "summary": "Revoke Token (RFC 7009)",
                "description": "ยกเลิก access_token หรือ refresh_token ส่ง client credentials ใน HTTP Basic auth หรือ body",
                "operationId": "oauthRevoke",
                "requestBody": {
                    "required": true,
                    "content": {
                        "application/x-www-form-urlencoded": {
                            "schema": {
                                "required": [
                                    "token"
                                ],
                                "properties": {
                                    "token": {
                                        "description": "access_token หรือ refresh_token ที่ต้องการยกเลิก",
                                        "type": "string"
                                    },
                                    "client_id": {
                                        "type": "string"
                                    },
                                    "client_secret": {
                                        "type": "string"
                                    }
                                },
                                "type": "object"
                            }
                        }
                    }
                },
                "responses": {
                    "200": {
                        "description": "สำเร็จ (RFC 7009: 200 เสมอแม้ token ไม่พบ)"
                    },
                    "401": {
                        "description": "invalid_client"
                    }
                }
            }
        },
        "/v1/me": {
            "get": {
                "tags": [
                    "Me (OAuth)"
                ],
                "summary": "โปรไฟล์ผู้ใช้ที่ authenticated",
                "description": "คืนข้อมูลโปรไฟล์ของผู้ใช้ที่ส่ง OAuth Bearer token มา\n\n**Required scope:** `profile` หรือ `openid`",
                "operationId": "meShow",
                "responses": {
                    "200": {
                        "description": "ข้อมูลโปรไฟล์",
                        "content": {
                            "application/json": {
                                "schema": {
                                    "properties": {
                                        "id": {
                                            "type": "integer",
                                            "example": 1
                                        },
                                        "username": {
                                            "type": "string",
                                            "example": "john.doe"
                                        },
                                        "name": {
                                            "type": "string",
                                            "example": "John Doe"
                                        },
                                        "email": {
                                            "type": "string",
                                            "example": "john@company.com",
                                            "nullable": true
                                        },
                                        "department": {
                                            "type": "string",
                                            "example": "IT",
                                            "nullable": true
                                        },
                                        "title": {
                                            "type": "string",
                                            "example": "Developer",
                                            "nullable": true
                                        },
                                        "employee_number": {
                                            "type": "string",
                                            "example": "EMP001",
                                            "nullable": true
                                        },
                                        "is_admin": {
                                            "type": "integer",
                                            "example": 0
                                        },
                                        "is_active": {
                                            "type": "boolean",
                                            "example": true
                                        },
                                        "last_login_at": {
                                            "type": "string",
                                            "format": "date-time",
                                            "nullable": true
                                        }
                                    },
                                    "type": "object"
                                }
                            }
                        }
                    },
                    "401": {
                        "description": "unauthorized / invalid_token"
                    },
                    "403": {
                        "description": "insufficient_scope"
                    }
                },
                "security": [
                    {
                        "oauthBearer": []
                    }
                ]
            }
        },
        "/v1/me/permissions": {
            "get": {
                "tags": [
                    "Me (OAuth)"
                ],
                "summary": "Permissions ของผู้ใช้ในระบบนี้",
                "description": "คืนรายการ permissions ของผู้ใช้ในระบบที่ตรงกับ OAuth client slug\n\n**Required scope:** `permissions`",
                "operationId": "mePermissions",
                "responses": {
                    "200": {
                        "description": "Permissions",
                        "content": {
                            "application/json": {
                                "schema": {
                                    "properties": {
                                        "system": {
                                            "properties": {
                                                "id": {
                                                    "type": "integer",
                                                    "example": 3
                                                },
                                                "slug": {
                                                    "type": "string",
                                                    "example": "repair-system"
                                                },
                                                "name": {
                                                    "type": "string",
                                                    "example": "Repair System"
                                                }
                                            },
                                            "type": "object"
                                        },
                                        "permissions": {
                                            "type": "array",
                                            "items": {
                                                "type": "string"
                                            },
                                            "example": [
                                                "view_report",
                                                "approve"
                                            ]
                                        }
                                    },
                                    "type": "object"
                                }
                            }
                        }
                    },
                    "401": {
                        "description": "unauthorized / invalid_token"
                    },
                    "403": {
                        "description": "insufficient_scope"
                    }
                },
                "security": [
                    {
                        "oauthBearer": []
                    }
                ]
            }
        },
        "/v1/me/systems": {
            "get": {
                "tags": [
                    "Me (OAuth)"
                ],
                "summary": "ระบบทั้งหมดที่ผู้ใช้มีสิทธิ์",
                "description": "คืนรายการระบบ (active) ที่ผู้ใช้มี permission อย่างน้อยหนึ่งรายการ พร้อมรายการ permissions\n\n**Required scope:** `profile`",
                "operationId": "meSystems",
                "responses": {
                    "200": {
                        "description": "ระบบที่มีสิทธิ์",
                        "content": {
                            "application/json": {
                                "schema": {
                                    "properties": {
                                        "systems": {
                                            "type": "array",
                                            "items": {
                                                "properties": {
                                                    "id": {
                                                        "type": "integer",
                                                        "example": 3
                                                    },
                                                    "slug": {
                                                        "type": "string",
                                                        "example": "repair-system"
                                                    },
                                                    "name": {
                                                        "type": "string",
                                                        "example": "Repair System"
                                                    },
                                                    "permissions": {
                                                        "type": "array",
                                                        "items": {
                                                            "type": "string"
                                                        }
                                                    }
                                                },
                                                "type": "object"
                                            }
                                        }
                                    },
                                    "type": "object"
                                }
                            }
                        }
                    },
                    "401": {
                        "description": "unauthorized / invalid_token"
                    },
                    "403": {
                        "description": "insufficient_scope"
                    }
                },
                "security": [
                    {
                        "oauthBearer": []
                    }
                ]
            }
        }
    },
    "components": {
        "schemas": {
            "UserProfile": {
                "properties": {
                    "username": {
                        "type": "string",
                        "example": "john.doe"
                    },
                    "name": {
                        "type": "string",
                        "example": "John Doe"
                    },
                    "email": {
                        "type": "string",
                        "format": "email",
                        "example": "john@company.com"
                    },
                    "department": {
                        "type": "string",
                        "example": "IT",
                        "nullable": true
                    },
                    "title": {
                        "type": "string",
                        "example": "Developer",
                        "nullable": true
                    }
                },
                "type": "object"
            },
            "ErrorResponse": {
                "properties": {
                    "message": {
                        "type": "string",
                        "example": "Invalid credentials"
                    }
                },
                "type": "object"
            },
            "ValidationError": {
                "properties": {
                    "message": {
                        "type": "string",
                        "example": "The username field is required."
                    },
                    "errors": {
                        "type": "object",
                        "additionalProperties": {
                            "type": "array",
                            "items": {
                                "type": "string"
                            }
                        }
                    }
                },
                "type": "object"
            }
        },
        "securitySchemes": {
            "bearerAuth": {
                "type": "http",
                "description": "Sanctum Bearer Token — รับได้จาก POST /api/auth/token หรือ POST /api/auth/user-login",
                "bearerFormat": "Sanctum Token",
                "scheme": "bearer"
            },
            "oauthBearer": {
                "type": "http",
                "description": "OAuth 2.0 Access Token (RS256 JWT) — รับได้จาก POST /api/oauth/token",
                "bearerFormat": "RS256 JWT",
                "scheme": "bearer"
            }
        }
    },
    "tags": [
        {
            "name": "Authentication",
            "description": "Login, logout และออก Sanctum token (legacy)"
        },
        {
            "name": "OAuth 2.0",
            "description": "Token endpoint สำหรับ OAuth 2.0 / OIDC"
        },
        {
            "name": "Me (OAuth)",
            "description": "ข้อมูลผู้ใช้ที่ authenticated ด้วย OAuth Bearer token"
        },
        {
            "name": "Permissions",
            "description": "ตรวจสอบและดึง permissions ของผู้ใช้"
        },
        {
            "name": "Export",
            "description": "ส่งออกข้อมูลผู้ใช้ + permissions ทุกระบบ"
        }
    ]
}